refract/__init__.py
refract/json.py
refract/refraction.py
refract/registry.py
refract/contrib/__init__.py
refract/contrib/apielements.py
refract/elements/__init__.py
refract/elements/array.py
refract/elements/base.py
refract/elements/object.py
refract/elements/primitives.py
refract-0.4.0.dist-info/LICENSE
refract-0.4.0.dist-info/METADATA
refract-0.4.0.dist-info/WHEEL
refract-0.4.0.dist-info/top_level.txt
refract-0.4.0.dist-info/RECORD
