Metadata-Version: 2.1
Name: refract
Version: 0.4.0
Summary: A Python library for interacting with Refract.
Home-page: https://github.com/kylef/refract.py
Author: Kyle Fuller
Author-email: kyle@fuller.li
License: BSD
Platform: UNKNOWN
Classifier: Development Status :: 5 - Production/Stable
Classifier: Programming Language :: Python :: 3.6
Classifier: Programming Language :: Python :: 3.7
Classifier: License :: OSI Approved :: BSD License
